[
  {
    "benchmark" : "MapOfIntsToBooleansWriting.avSystemGenCodec",
    "mode" : "thrpt",
    "threads" : 1,
    "forks" : 1,
    "jdkVersion" : "1.8",
    "vmName" : "Scala.JS",
    "vmVersion" : "1.11.0",
    "userAgent" : "Mozilla/5.0 (X11; Ubuntu; Linux x86_64; rv:105.0) Gecko/20100101 Firefox/105.0",
    "warmupIterations" : 5,
    "warmupTime" : "1 s",
    "warmupBatchSize" : 1,
    "measurementIterations" : 5,
    "measurementTime" : "1 s",
    "measurementBatchSize" : 1,
    "primaryMetric" : {
      "score" : 12284.4,
      "scoreError" : 788.7177245666911,
      "scoreConfidence" : [
        11495.682275433308,
        13073.117724566691
      ],
      "scoreUnit" : "ops/s",
      "rawData" : [
        [
          12403,
          12387,
          12324,
          12385.999999999998,
          11922
        ]
      ]
    },
    "secondaryMetrics" : {
    }
  },
  {
    "benchmark" : "MapOfIntsToBooleansWriting.circe",
    "mode" : "thrpt",
    "threads" : 1,
    "forks" : 1,
    "jdkVersion" : "1.8",
    "vmName" : "Scala.JS",
    "vmVersion" : "1.11.0",
    "userAgent" : "Mozilla/5.0 (X11; Ubuntu; Linux x86_64; rv:105.0) Gecko/20100101 Firefox/105.0",
    "warmupIterations" : 5,
    "warmupTime" : "1 s",
    "warmupBatchSize" : 1,
    "measurementIterations" : 5,
    "measurementTime" : "1 s",
    "measurementBatchSize" : 1,
    "primaryMetric" : {
      "score" : 3542.4,
      "scoreError" : 259.5773880923183,
      "scoreConfidence" : [
        3282.8226119076817,
        3801.9773880923185
      ],
      "scoreUnit" : "ops/s",
      "rawData" : [
        [
          3508,
          3554,
          3532,
          3469,
          3648.9999999999995
        ]
      ]
    },
    "secondaryMetrics" : {
    }
  },
  {
    "benchmark" : "MapOfIntsToBooleansWriting.circeJsoniter",
    "mode" : "thrpt",
    "threads" : 1,
    "forks" : 1,
    "jdkVersion" : "1.8",
    "vmName" : "Scala.JS",
    "vmVersion" : "1.11.0",
    "userAgent" : "Mozilla/5.0 (X11; Ubuntu; Linux x86_64; rv:105.0) Gecko/20100101 Firefox/105.0",
    "warmupIterations" : 5,
    "warmupTime" : "1 s",
    "warmupBatchSize" : 1,
    "measurementIterations" : 5,
    "measurementTime" : "1 s",
    "measurementBatchSize" : 1,
    "primaryMetric" : {
      "score" : 4392.542657342658,
      "scoreError" : 644.766782350122,
      "scoreConfidence" : [
        3747.7758749925356,
        5037.309439692779
      ],
      "scoreUnit" : "ops/s",
      "rawData" : [
        [
          4575,
          4286.713286713287,
          4228,
          4572,
          4301
        ]
      ]
    },
    "secondaryMetrics" : {
    }
  },
  {
    "benchmark" : "MapOfIntsToBooleansWriting.jsoniterScala",
    "mode" : "thrpt",
    "threads" : 1,
    "forks" : 1,
    "jdkVersion" : "1.8",
    "vmName" : "Scala.JS",
    "vmVersion" : "1.11.0",
    "userAgent" : "Mozilla/5.0 (X11; Ubuntu; Linux x86_64; rv:105.0) Gecko/20100101 Firefox/105.0",
    "warmupIterations" : 5,
    "warmupTime" : "1 s",
    "warmupBatchSize" : 1,
    "measurementIterations" : 5,
    "measurementTime" : "1 s",
    "measurementBatchSize" : 1,
    "primaryMetric" : {
      "score" : 85537.6,
      "scoreError" : 1640.0683124909638,
      "scoreConfidence" : [
        83897.53168750904,
        87177.66831249098
      ],
      "scoreUnit" : "ops/s",
      "rawData" : [
        [
          85556,
          85497,
          84964,
          85506,
          86165
        ]
      ]
    },
    "secondaryMetrics" : {
    }
  },
  {
    "benchmark" : "MapOfIntsToBooleansWriting.jsoniterScalaPrealloc",
    "mode" : "thrpt",
    "threads" : 1,
    "forks" : 1,
    "jdkVersion" : "1.8",
    "vmName" : "Scala.JS",
    "vmVersion" : "1.11.0",
    "userAgent" : "Mozilla/5.0 (X11; Ubuntu; Linux x86_64; rv:105.0) Gecko/20100101 Firefox/105.0",
    "warmupIterations" : 5,
    "warmupTime" : "1 s",
    "warmupBatchSize" : 1,
    "measurementIterations" : 5,
    "measurementTime" : "1 s",
    "measurementBatchSize" : 1,
    "primaryMetric" : {
      "score" : 94446.6,
      "scoreError" : 1218.4157843080577,
      "scoreConfidence" : [
        93228.18421569194,
        95665.01578430807
      ],
      "scoreUnit" : "ops/s",
      "rawData" : [
        [
          94535.00000000001,
          94755,
          93999,
          94253,
          94691
        ]
      ]
    },
    "secondaryMetrics" : {
    }
  },
  {
    "benchmark" : "MapOfIntsToBooleansWriting.smithy4sJson",
    "mode" : "thrpt",
    "threads" : 1,
    "forks" : 1,
    "jdkVersion" : "1.8",
    "vmName" : "Scala.JS",
    "vmVersion" : "1.11.0",
    "userAgent" : "Mozilla/5.0 (X11; Ubuntu; Linux x86_64; rv:105.0) Gecko/20100101 Firefox/105.0",
    "warmupIterations" : 5,
    "warmupTime" : "1 s",
    "warmupBatchSize" : 1,
    "measurementIterations" : 5,
    "measurementTime" : "1 s",
    "measurementBatchSize" : 1,
    "primaryMetric" : {
      "score" : 70960.2,
      "scoreError" : 1037.5731374476607,
      "scoreConfidence" : [
        69922.62686255234,
        71997.77313744766
      ],
      "scoreUnit" : "ops/s",
      "rawData" : [
        [
          71105,
          70827,
          70563,
          71054,
          71252
        ]
      ]
    },
    "secondaryMetrics" : {
    }
  },
  {
    "benchmark" : "MapOfIntsToBooleansWriting.zioJson",
    "mode" : "thrpt",
    "threads" : 1,
    "forks" : 1,
    "jdkVersion" : "1.8",
    "vmName" : "Scala.JS",
    "vmVersion" : "1.11.0",
    "userAgent" : "Mozilla/5.0 (X11; Ubuntu; Linux x86_64; rv:105.0) Gecko/20100101 Firefox/105.0",
    "warmupIterations" : 5,
    "warmupTime" : "1 s",
    "warmupBatchSize" : 1,
    "measurementIterations" : 5,
    "measurementTime" : "1 s",
    "measurementBatchSize" : 1,
    "primaryMetric" : {
      "score" : 12397.4,
      "scoreError" : 764.9592738836029,
      "scoreConfidence" : [
        11632.440726116396,
        13162.359273883603
      ],
      "scoreUnit" : "ops/s",
      "rawData" : [
        [
          12474,
          12462.000000000002,
          12536,
          12469,
          12046
        ]
      ]
    },
    "secondaryMetrics" : {
    }
  }
]